sigma/analyze/attack.py
sigma/analyze/fields.py
sigma/analyze/stats.py
sigma/cli/analyze.py
sigma/cli/check.py
sigma/cli/convert.py
sigma/cli/list.py
sigma/cli/main.py
sigma/cli/plugin.py
sigma/cli/pysigma.py
sigma/cli/rules.py
sigma_cli-2.0.1.dist-info/METADATA
sigma_cli-2.0.1.dist-info/WHEEL
sigma_cli-2.0.1.dist-info/entry_points.txt
sigma_cli-2.0.1.dist-info/RECORD
