Metadata-Version: 2.4
Name: sigma-cli
Version: 2.0.1
Summary: Sigma Command Line Interface (conversion, check etc.) based on pySigma
License: LGPL-2.1-or-later
Author: Thomas Patzke
Author-email: thomas@patzke.org
Requires-Python: >=3.10,<4.0
Classifier: Development Status :: 4 - Beta
Classifier: Intended Audience :: System Administrators
Classifier: License :: OSI Approved
Classifier: License :: OSI Approved :: GNU Lesser General Public License v2 (LGPLv2)
Classifier: Programming Language :: Python :: 3
Classifier: Programming Language :: Python :: 3.10
Classifier: Programming Language :: Python :: 3.11
Classifier: Programming Language :: Python :: 3.12
Classifier: Programming Language :: Python :: 3.13
Classifier: Programming Language :: Python :: 3.14
Classifier: Programming Language :: Python :: 3.8
Classifier: Programming Language :: Python :: 3.9
Classifier: Topic :: Security
Requires-Dist: click (>=8.3.1,<9.0.0)
Requires-Dist: colorama (>=0.4.6,<0.5.0)
Requires-Dist: prettytable (>=3.17.0,<4.0.0)
Requires-Dist: pysigma (>=1,<2)
Project-URL: Repository, https://github.com/SigmaHQ/sigma-cli
